QMzyme/QM_region_analysis.py
QMzyme/__init__.py
QMzyme/_version.py
QMzyme/aqme_wrapper.py
QMzyme/generate.py
QMzyme/mdanalysis_wrapper.py
QMzyme/old_generate.py
QMzyme/protein_parser.py
QMzyme/py.typed
QMzyme/rdkit_wrapper.py
QMzyme/utils.py
QMzyme/data/__init__.py
tests/__init__.py
tests/test_QMzyme.py
QMzyme-0.9.34.dist-info/LICENSE
QMzyme-0.9.34.dist-info/METADATA
QMzyme-0.9.34.dist-info/WHEEL
QMzyme-0.9.34.dist-info/top_level.txt
QMzyme-0.9.34.dist-info/RECORD
