Metadata-Version: 2.1
Name: QMzyme
Version: 0.9.34
Summary: QM-based enzyme model generation and validation.
Author-email: Heidi Klem <heidi.klem@nist.gov>
License: MIT
Classifier: License :: OSI Approved :: MIT License
Classifier: Programming Language :: Python :: 3
Requires-Python: >=3.0
License-File: LICENSE
Requires-Dist: importlib-resources
Requires-Dist: rdkit
Requires-Dist: numpy
Requires-Dist: aqme
Provides-Extra: mda
Requires-Dist: MDAnalysis ; extra == 'mda'
